philly_cheesesnake/__init__.py
philly_cheesesnake/__main__.py
philly_cheesesnake/loaders.py
philly_cheesesnake/philly_cheesesnake.py
philly_cheesesnake/datasets/2009-2012_Police_Advisory_Commission_Complaints.yaml
philly_cheesesnake/datasets/2015_Parking_Meter___Kiosk_Inventory.yaml
philly_cheesesnake/datasets/2020_Census_to_Police_District_Crosswalk.yaml
philly_cheesesnake/datasets/311_Service_and_Information_Requests.yaml
philly_cheesesnake/datasets/AMS_Latest_Air_Quality_Sensor_Readings.yaml
philly_cheesesnake/datasets/ARCHIVED__2007-2015_Litter_Index.yaml
philly_cheesesnake/datasets/ARCHIVED__Greenworks_Metrics.yaml
philly_cheesesnake/datasets/ARCHIVED__Healthy_Chinese_Takeout.yaml
philly_cheesesnake/datasets/ARCHIVED__Philadelphia_Food_Access.yaml
philly_cheesesnake/datasets/ARCHIVED__Valet_Parking_Locations.yaml
philly_cheesesnake/datasets/Active_Residential_Parking_Permits_by_District.yaml
philly_cheesesnake/datasets/Advancing_Education_Safely.yaml
philly_cheesesnake/datasets/Aerial_Photography__imagery_.yaml
philly_cheesesnake/datasets/Affordable_Housing_Production.yaml
philly_cheesesnake/datasets/Air_Monitoring_Stations.yaml
philly_cheesesnake/datasets/Air_Quality_Index_Days.yaml
philly_cheesesnake/datasets/Arterial_Streets.yaml
philly_cheesesnake/datasets/Big_Belly_Trash_Bin_Usage.yaml
philly_cheesesnake/datasets/Big_Belly_Waste_Baskets__Trash_Bins_.yaml
philly_cheesesnake/datasets/Bike_Network.yaml
philly_cheesesnake/datasets/Bike_Network_-_Supporting_Datasets.yaml
philly_cheesesnake/datasets/Boost_Your_Business_Program.yaml
philly_cheesesnake/datasets/Bridge_Locations.yaml
philly_cheesesnake/datasets/Building_Demolitions.yaml
philly_cheesesnake/datasets/Building_Footprints.yaml
philly_cheesesnake/datasets/Bullet_Voting_2015.yaml
philly_cheesesnake/datasets/Bus_Shelters.yaml
philly_cheesesnake/datasets/Business_Improvement_Districts__BID_.yaml
philly_cheesesnake/datasets/Business_Technical_Support_Resources.yaml
philly_cheesesnake-0.1.0.dist-info/licenses/LICENSE
philly_cheesesnake-0.1.0.dist-info/METADATA
philly_cheesesnake-0.1.0.dist-info/WHEEL
philly_cheesesnake-0.1.0.dist-info/entry_points.txt
philly_cheesesnake-0.1.0.dist-info/top_level.txt
philly_cheesesnake-0.1.0.dist-info/RECORD
